{
  "docs": [
    {
      "externalId": {
        "kpHD": "4df03a8ddb64d11d99a2611bf39ac776",
        "imdb": "tt3783958",
        "tmdb": 313369
      },
      "rating": {
        "kp": 7.961,
        "imdb": 8,
        "filmCritics": 8.7,
        "russianFilmCritics": 100,
        "await": null
      },
      "votes": {
        "kp": 297476,
        "imdb": 611925,
        "filmCritics": 470,
        "russianFilmCritics": 32,
        "await": 11702
      },
      "movieLength": 128,
      "id": 841081,
      "type": "movie",
      "name": "\u041b\u0430-\u041b\u0430 \u041b\u0435\u043d\u0434",
      "description": "\u042d\u0442\u043e \u0438\u0441\u0442\u043e\u0440\u0438\u044f \u043b\u044e\u0431\u0432\u0438 \u0441\u0442\u0430\u0440\u043b\u0435\u0442\u043a\u0438, \u043a\u043e\u0442\u043e\u0440\u0430\u044f \u043c\u0435\u0436\u0434\u0443 \u043f\u0440\u043e\u0441\u043b\u0443\u0448\u0438\u0432\u0430\u043d\u0438\u044f\u043c\u0438 \u043f\u043e\u0434\u0430\u0435\u0442 \u043a\u043e\u0444\u0435 \u0441\u043e\u0441\u0442\u043e\u044f\u0432\u0448\u0438\u043c\u0441\u044f \u043a\u0438\u043d\u043e\u0437\u0432\u0435\u0437\u0434\u0430\u043c, \u0438 \u0444\u0430\u043d\u0430\u0442\u0438\u0447\u043d\u043e\u0433\u043e \u0434\u0436\u0430\u0437\u043e\u0432\u043e\u0433\u043e \u043c\u0443\u0437\u044b\u043a\u0430\u043d\u0442\u0430, \u0432\u044b\u043d\u0443\u0436\u0434\u0435\u043d\u043d\u043e\u0433\u043e \u043f\u043e\u0434\u0440\u0430\u0431\u0430\u0442\u044b\u0432\u0430\u0442\u044c \u0432 \u0437\u0430\u0448\u0442\u0430\u0442\u043d\u044b\u0445 \u0431\u0430\u0440\u0430\u0445. \u041d\u043e \u043f\u0440\u0438\u0448\u0435\u0434\u0448\u0438\u0439 \u043a \u0432\u043b\u044e\u0431\u043b\u0435\u043d\u043d\u044b\u043c \u0443\u0441\u043f\u0435\u0445 \u043d\u0430\u0447\u0438\u043d\u0430\u0435\u0442 \u043f\u043e\u0434\u0442\u0430\u0447\u0438\u0432\u0430\u0442\u044c \u0438\u0445 \u043e\u0442\u043d\u043e\u0448\u0435\u043d\u0438\u044f.",
      "year": 2016,
      "poster": {
        "url": "https://st.kp.yandex.net/images/film_big/841081.jpg",
        "previewUrl": "https://st.kp.yandex.net/images/film_iphone/iphone360_841081.jpg"
      },
      "genres": [
        {
          "name": "\u043c\u044e\u0437\u0438\u043a\u043b"
        },
        {
          "name": "\u0434\u0440\u0430\u043c\u0430"
        },
        {
          "name": "\u043c\u0435\u043b\u043e\u0434\u0440\u0430\u043c\u0430"
        },
        {
          "name": "\u043a\u043e\u043c\u0435\u0434\u0438\u044f"
        },
        {
          "name": "\u043c\u0443\u0437\u044b\u043a\u0430"
        }
      ],
      "countries": [
        {
          "name": "\u0421\u0428\u0410"
        },
        {
          "name": "\u0413\u043e\u043d\u043a\u043e\u043d\u0433"
        }
      ],
      "alternativeName": "La La Land",
      "enName": null,
      "names": [
        {
          "name": "\u041b\u0430-\u041b\u0430 \u041b\u0435\u043d\u0434"
        },
        {
          "name": "La La Land"
        }
      ],
      "shortDescription": "\u041c\u0438\u0430 \u0438 \u0421\u0435\u0431\u0430\u0441\u0442\u044c\u044f\u043d \u0432\u044b\u0431\u0438\u0440\u0430\u044e\u0442 \u043c\u0435\u0436\u0434\u0443 \u043b\u0438\u0447\u043d\u044b\u043c \u0441\u0447\u0430\u0441\u0442\u044c\u0435\u043c \u0438 \u0430\u043c\u0431\u0438\u0446\u0438\u044f\u043c\u0438. \u0422\u0440\u0430\u0433\u0438\u043a\u043e\u043c\u0438\u0447\u043d\u044b\u0439 \u043c\u044e\u0437\u0438\u043a\u043b \u043e \u043a\u043e\u043c\u043f\u0440\u043e\u043c\u0438\u0441\u0441\u0435 \u0432 \u0436\u0438\u0437\u043d\u0438 \u0430\u0440\u0442\u0438\u0441\u0442\u0430",
      "logo": {
        "url": "https://avatars.mds.yandex.net/get-ott/224348/2a0000017ae7b37ade35f66d7eb5425793e3/orig"
      },
      "watchability": {
        "items": [
          {
            "name": "Okko",
            "logo": {
              "url": "https://avatars.mds.yandex.net/get-ott/239697/7713e586-17d1-42d1-ac62-53e9ef1e70c3/orig"
            },
            "url": "https://okko.tv/movie/la-la-land?utm_medium=referral&utm_source=yandex_search&utm_campaign=new_search_feed"
          },
          {
            "name": "\u0418\u0432\u0438",
            "logo": {
              "url": "https://avatars.mds.yandex.net/get-ott/2419418/0dfd1724-848f-4725-9160-abc571f41c11/orig"
            },
            "url": "https://www.ivi.ru/watch/136478?utm_source=yandex&utm_medium=wizard"
          },
          {
            "name": "KION",
            "logo": {
              "url": "https://avatars.mds.yandex.net/get-ott/239697/daeb142e-3ecc-4bb2-9bff-4827996643ab/orig"
            },
            "url": "https://kion.ru/video/movie/508626897?utm_source=yandex&utm_medium=organic&utm_campaign=wizard"
          },
          {
            "name": "PREMIER",
            "logo": {
              "url": "https://avatars.mds.yandex.net/get-ott/239697/0f86e907-9531-47e9-87bd-5101a08d4e30/orig"
            },
            "url": "https://premier.one/show/8721?utm_source=yandex&utm_medium=yandex_feed_search&utm_campaign=yandex_feed"
          },
          {
            "name": "Wink",
            "logo": {
              "url": "https://avatars.mds.yandex.net/get-ott/1672343/54096cbe-cc3b-41c9-8e44-990ebbca8d61/orig"
            },
            "url": "https://wink.ru/media_items/54783645?utm_source=yandex&utm_medium=koldunschick&utm_content=name"
          }
        ]
      }
    },
    {
      "externalId": {
        "kpHD": "41453bbbf65bdbeea6e7b803e2f1ab88",
        "imdb": "tt6105098",
        "tmdb": 420818
      },
      "rating": {
        "kp": 7.207,
        "imdb": 6.8,
        "filmCritics": 6,
        "russianFilmCritics": 44.4444,
        "await": null
      },
      "votes": {
        "kp": 284392,
        "imdb": 252901,
        "filmCritics": 435,
        "russianFilmCritics": 9,
        "await": 32905
      },
      "movieLength": 118,
      "id": 1005878,
      "type": "cartoon",
      "name": "\u041a\u043e\u0440\u043e\u043b\u044c \u041b\u0435\u0432",
      "description": "\u0418\u0441\u0442\u043e\u0440\u0438\u044f \u043e\u0431 \u043e\u0442\u0432\u0430\u0436\u043d\u043e\u043c \u043b\u044c\u0432\u0435\u043d\u043a\u0435 \u043f\u043e \u0438\u043c\u0435\u043d\u0438 \u0421\u0438\u043c\u0431\u0430. \u0417\u043d\u0430\u043a\u043e\u043c\u044b\u0435 \u0441 \u0434\u0435\u0442\u0441\u0442\u0432\u0430 \u0433\u0435\u0440\u043e\u0438 \u0432\u0437\u0440\u043e\u0441\u043b\u0435\u044e\u0442, \u0432\u043b\u044e\u0431\u043b\u044f\u044e\u0442\u0441\u044f, \u043f\u043e\u0437\u043d\u0430\u044e\u0442 \u0441\u0435\u0431\u044f \u0438 \u043e\u043a\u0440\u0443\u0436\u0430\u044e\u0449\u0438\u0439 \u043c\u0438\u0440, \u0441\u043e\u0432\u0435\u0440\u0448\u0430\u044e\u0442 \u043e\u0448\u0438\u0431\u043a\u0438 \u0438 \u0434\u0435\u043b\u0430\u044e\u0442 \u043f\u0440\u0430\u0432\u0438\u043b\u044c\u043d\u044b\u0439 \u0432\u044b\u0431\u043e\u0440.",
      "year": 2019,
      "poster": {
        "url": "https://st.kp.yandex.net/images/film_big/1005878.jpg",
        "previewUrl": "https://st.kp.yandex.net/images/film_iphone/iphone360_1005878.jpg"
      },
      "genres": [
        {
          "name": "\u043c\u0443\u043b\u044c\u0442\u0444\u0438\u043b\u044c\u043c"
        },
        {
          "name": "\u043c\u044e\u0437\u0438\u043a\u043b"
        },
        {
          "name": "\u0434\u0440\u0430\u043c\u0430"
        },
        {
          "name": "\u043f\u0440\u0438\u043a\u043b\u044e\u0447\u0435\u043d\u0438\u044f"
        },
        {
          "name": "\u0441\u0435\u043c\u0435\u0439\u043d\u044b\u0439"
        }
      ],
      "countries": [
        {
          "name": "\u0421\u0428\u0410"
        },
        {
          "name": "\u0412\u0435\u043b\u0438\u043a\u043e\u0431\u0440\u0438\u0442\u0430\u043d\u0438\u044f"
        }
      ],
      "alternativeName": "The Lion King",
      "enName": null,
      "names": [
        {
          "name": "\u041a\u043e\u0440\u043e\u043b\u044c \u041b\u0435\u0432"
        },
        {
          "name": "The Lion King"
        },
        {
          "name": "O Vasili\u00e1s Ton Liontari\u00f3n",
          "language": "GR",
          "type": null
        },
        {
          "name": "Kr\u00f3l Lew",
          "language": "PL",
          "type": null
        },
        {
          "name": "Der K\u00f6nig der L\u00f6wen",
          "language": "DE",
          "type": null
        }
      ],
      "shortDescription": "\u0421\u0447\u0430\u0441\u0442\u043b\u0438\u0432\u0443\u044e \u0436\u0438\u0437\u043d\u044c \u0432 \u043c\u0438\u0440\u0435 \u0436\u0438\u0432\u043e\u0442\u043d\u044b\u0445 \u0440\u0430\u0437\u0440\u0443\u0448\u0430\u0435\u0442 \u0431\u0440\u0430\u0442\u0441\u043a\u0430\u044f \u0437\u0430\u0432\u0438\u0441\u0442\u044c. \u0424\u043e\u0442\u043e\u0440\u0435\u0430\u043b\u0438\u0441\u0442\u0438\u0447\u043d\u044b\u0439 \u0440\u0435\u043c\u0435\u0439\u043a \u0437\u043d\u0430\u043c\u0435\u043d\u0438\u0442\u043e\u0433\u043e \u0445\u0438\u0442\u0430 Disney",
      "logo": {
        "url": "https://avatars.mds.yandex.net/get-ott/1672343/2a0000016e043a3ddb1534f8dcbe20d07b2a/orig"
      },
      "watchability": {
        "items": [
          {
            "name": "24\u0422\u0412",
            "logo": {
              "url": "https://avatars.mds.yandex.net/get-ott/2439731/85e83b8d-1159-4781-bad5-ce0a809b3843/orig"
            },
            "url": "https://24h.tv/contents/2019-the-lion-king-546396155680916062"
          }
        ]
      }
    },
    {
      "id": 5277,
      "type": "cartoon",
      "externalId": {
        "kpHD": "4a920894c1306794aacf6896ca459e41",
        "imdb": "tt0120762",
        "tmdb": 10674
      },
      "name": "\u041c\u0443\u043b\u0430\u043d",
      "rating": {
        "kp": 8.132,
        "imdb": 7.6,
        "filmCritics": 7.6,
        "russianFilmCritics": 0,
        "await": null
      },
      "description": "\u0414\u043b\u044f \u0432\u0435\u043b\u0438\u043a\u043e\u0433\u043e \u043d\u0430\u0440\u043e\u0434\u0430 \u043d\u0430\u0441\u0442\u0443\u043f\u0438\u043b\u0438 \u0442\u044f\u0436\u0435\u043b\u044b\u0435 \u0432\u0440\u0435\u043c\u0435\u043d\u0430: \u043d\u0430 \u0441\u0442\u0440\u0430\u043d\u0443 \u043d\u0430\u043f\u0430\u043b\u043e \u0432\u043e\u0438\u043d\u0441\u0442\u0432\u0435\u043d\u043d\u043e\u0435 \u043f\u043b\u0435\u043c\u044f \u0433\u0443\u043d\u043d\u043e\u0432. \u041f\u0435\u0440\u0435\u043e\u0434\u0435\u0432\u0448\u0438\u0441\u044c \u0432 \u043c\u0443\u0436\u0441\u043a\u0443\u044e \u043e\u0434\u0435\u0436\u0434\u0443, \u041c\u0443\u043b\u0430\u043d \u043f\u0440\u0438\u0441\u043e\u0435\u0434\u0438\u043d\u044f\u0435\u0442\u0441\u044f \u043a \u0434\u0440\u0443\u0433\u0438\u043c \u0432\u043e\u0438\u043d\u0430\u043c \u0438 \u043e\u0442\u043f\u0440\u0430\u0432\u043b\u044f\u0435\u0442\u0441\u044f \u0432 \u043e\u043f\u0430\u0441\u043d\u044b\u0439 \u043f\u043e\u0445\u043e\u0434 \u043a \u043f\u043e\u0434\u043d\u043e\u0436\u0438\u044e \u0437\u0430\u0441\u043d\u0435\u0436\u0435\u043d\u043d\u044b\u0445 \u0433\u043e\u0440. \u0415\u0435 \u0441\u043e\u043f\u0440\u043e\u0432\u043e\u0436\u0434\u0430\u0435\u0442 \u0437\u0430\u0431\u0430\u0432\u043d\u044b\u0439 \u0434\u0440\u0430\u043a\u043e\u043d\u0447\u0438\u043a \u041c\u0443\u0448\u0443, \u043a\u043e\u0442\u043e\u0440\u044b\u0439 \u0431\u043e\u043b\u044c\u0448\u0435 \u043f\u043e\u0445\u043e\u0436 \u043d\u0430 \u043c\u0430\u043b\u0435\u043d\u044c\u043a\u0443\u044e \u0441\u043e\u0431\u0430\u0447\u043a\u0443, \u0447\u0435\u043c \u043d\u0430 \u043c\u0438\u0444\u0438\u0447\u0435\u0441\u043a\u043e\u0435 \u0447\u0443\u0434\u043e\u0432\u0438\u0449\u0435. \n\n\u041f\u044b\u0442\u0430\u044f\u0441\u044c \u0441\u043a\u0440\u044b\u0442\u044c \u0442\u0430\u0439\u043d\u0443, \u043e\u043d\u0438 \u043f\u043e\u043f\u0430\u0434\u0430\u044e\u0442 \u0432 \u0437\u0430\u0431\u0430\u0432\u043d\u044b\u0435 \u0441\u0438\u0442\u0443\u0430\u0446\u0438\u0438 \u0438 \u043d\u0435 \u043f\u043e\u0434\u043e\u0437\u0440\u0435\u0432\u0430\u044e\u0442, \u0447\u0442\u043e \u0438\u0445 \u0441\u0435\u043a\u0440\u0435\u0442 \u0432\u043e\u0442 - \u0432\u043e\u0442 \u0440\u0430\u0441\u043a\u0440\u043e\u0435\u0442\u0441\u044f!...",
      "votes": {
        "kp": 282160,
        "imdb": 297616,
        "filmCritics": 84,
        "russianFilmCritics": 0,
        "await": 0
      },
      "year": 1998,
      "poster": {
        "url": "https://st.kp.yandex.net/images/film_big/5277.jpg",
        "previewUrl": "https://st.kp.yandex.net/images/film_iphone/iphone360_5277.jpg"
      },
      "genres": [
        {
          "name": "\u043c\u0443\u043b\u044c\u0442\u0444\u0438\u043b\u044c\u043c"
        },
        {
          "name": "\u043c\u044e\u0437\u0438\u043a\u043b"
        },
        {
          "name": "\u0444\u044d\u043d\u0442\u0435\u0437\u0438"
        },
        {
          "name": "\u043a\u043e\u043c\u0435\u0434\u0438\u044f"
        },
        {
          "name": "\u043f\u0440\u0438\u043a\u043b\u044e\u0447\u0435\u043d\u0438\u044f"
        },
        {
          "name": "\u0441\u0435\u043c\u0435\u0439\u043d\u044b\u0439"
        },
        {
          "name": "\u0432\u043e\u0435\u043d\u043d\u044b\u0439"
        }
      ],
      "countries": [
        {
          "name": "\u0421\u0428\u0410"
        },
        {
          "name": "\u042f\u043f\u043e\u043d\u0438\u044f"
        }
      ],
      "alternativeName": "Mulan",
      "enName": null,
      "movieLength": 84,
      "names": [
        {
          "name": "\u041c\u0443\u043b\u0430\u043d"
        },
        {
          "name": "Mulan"
        },
        {
          "name": "Walt Disney's Mulan",
          "language": "US",
          "type": null
        },
        {
          "name": "Legenda o Mulan",
          "language": "CZ",
          "type": null
        },
        {
          "name": "\ubbac\ub780",
          "language": "KR",
          "type": null
        },
        {
          "name": "Legenda o Mulan",
          "language": "SK",
          "type": null
        },
        {
          "name": "\u82b1\u6728\u5170",
          "language": "CN",
          "type": null
        },
        {
          "name": "Mul\u00e1n",
          "language": "CR",
          "type": null
        }
      ],
      "shortDescription": "\u041e\u0442\u0432\u0430\u0436\u043d\u0430\u044f \u0434\u0435\u0432\u0443\u0448\u043a\u0430 \u0442\u0430\u0439\u043d\u043e \u043e\u0442\u043f\u0440\u0430\u0432\u043b\u044f\u0435\u0442\u0441\u044f \u043d\u0430 \u0432\u043e\u0439\u043d\u0443 \u0432\u043c\u0435\u0441\u0442\u043e \u043e\u0442\u0446\u0430. \u0414\u0438\u0441\u043d\u0435\u0435\u0432\u0441\u043a\u0430\u044f \u0432\u0435\u0440\u0441\u0438\u044f \u0437\u0430\u0445\u0432\u0430\u0442\u044b\u0432\u0430\u044e\u0449\u0435\u0439 \u043a\u0438\u0442\u0430\u0439\u0441\u043a\u043e\u0439 \u043b\u0435\u0433\u0435\u043d\u0434\u044b",
      "logo": {
        "url": "https://avatars.mds.yandex.net/get-ott/2419418/2a0000016eadd29039bb943861ea47e3c306/orig"
      },
      "watchability": {
        "items": null
      }
    },
    {
      "externalId": {
        "kpHD": "4a93d993505ab93a97dc36abf882f3c4",
        "imdb": "tt6467266",
        "tmdb": 438695
      },
      "rating": {
        "kp": 8.308,
        "imdb": 7.4,
        "filmCritics": 6.1,
        "russianFilmCritics": 75,
        "await": null
      },
      "votes": {
        "kp": 271751,
        "imdb": 74783,
        "filmCritics": 137,
        "russianFilmCritics": 4,
        "await": 14324
      },
      "movieLength": 110,
      "id": 1009142,
      "type": "cartoon",
      "name": "\u0417\u0432\u0435\u0440\u043e\u043f\u043e\u0439 2",
      "description": "\u0422\u044f\u0436\u0435\u043b\u043e \u0431\u044b\u0442\u044c \u043f\u0440\u043e\u0434\u044e\u0441\u0435\u0440\u043e\u043c, \u043a\u043e\u0433\u0434\u0430 \u0442\u044b\u00a0\u043a\u043e\u0430\u043b\u0430 \u0438\u00a0\u0443 \u0442\u0435\u0431\u044f \u043b\u0430\u043f\u043a\u0438. \u0415\u0449\u0435\u00a0\u0441\u043b\u043e\u0436\u043d\u0435\u0435, \u043a\u043e\u0433\u0434\u0430 \u0442\u0432\u043e\u044f \u0432\u0435\u0440\u043d\u0430\u044f \u043f\u043e\u043c\u043e\u0449\u043d\u0438\u0446\u0430 \u0434\u0440\u0435\u0432\u043d\u0435\u0435 \u043f\u0435\u0447\u0430\u0442\u043d\u043e\u0439 \u043c\u0430\u0448\u0438\u043d\u043a\u0438. \u0418\u00a0\u0441\u043e\u0432\u0441\u0435\u043c \u0432\u0435\u0441\u0435\u043b\u043e, \u043a\u043e\u0433\u0434\u0430 \u0442\u0432\u043e\u044f \u0442\u0440\u0443\u043f\u043f\u0430\u00a0\u2014\u00a0\u044d\u0442\u043e \u0442\u0430\u043d\u0446\u0443\u044e\u0449\u0438\u0439 \u0431\u0435\u0437\u00a0\u043e\u0441\u0442\u0430\u043d\u043e\u0432\u043a\u0438 \u043f\u0443\u0445\u043b\u044f\u0448, \u043a\u043e\u043b\u044e\u0447\u0430\u044f \u0434\u0435\u0432\u043e\u0447\u043a\u0430-\u043f\u0430\u043d\u043a, \u0437\u0430\u0441\u0442\u0435\u043d\u0447\u0438\u0432\u0430\u044f \u0448\u043a\u043e\u043b\u044c\u043d\u0438\u0446\u0430, \u0432\u0435\u0440\u0437\u0438\u043b\u0430-\u0433\u0430\u043d\u0433\u0441\u0442\u0435\u0440 \u0438\u00a0\u043c\u043d\u043e\u0433\u043e\u0434\u0435\u0442\u043d\u0430\u044f \u043c\u0430\u043c\u0430, \u0447\u044c\u0438\u00a0\u0434\u0435\u0442\u0438\u00a0\u2014\u00a0\u043f\u043e\u0440\u043e\u0441\u044f\u0442\u0430 \u0432\u00a0\u043f\u0440\u044f\u043c\u043e\u043c \u0441\u043c\u044b\u0441\u043b\u0435 \u0441\u043b\u043e\u0432\u0430. \u0420\u0435\u0446\u0435\u043f\u0442 \u0443\u0441\u043f\u0435\u0445\u0430 \u043f\u0440\u043e\u0441\u0442\u00a0\u2014\u00a0\u0440\u0432\u0430\u043d\u0443\u0442\u044c \u0432\u00a0\u043c\u0438\u0440\u043e\u0432\u0443\u044e \u0441\u0442\u043e\u043b\u0438\u0446\u0443 \u0440\u0430\u0437\u0432\u043b\u0435\u0447\u0435\u043d\u0438\u0439, \u0437\u0430\u0432\u0435\u0440\u0431\u043e\u0432\u0430\u0442\u044c \u043b\u0435\u0433\u0435\u043d\u0434\u0430\u0440\u043d\u043e\u0433\u043e \u0440\u043e\u043a-\u043c\u0443\u0437\u044b\u043a\u0430\u043d\u0442\u0430 \u0438\u00a0\u0432\u0437\u043e\u0440\u0432\u0430\u0442\u044c \u0441\u0446\u0435\u043d\u0443 \u043d\u043e\u0432\u044b\u043c \u0448\u043e\u0443.",
      "year": 2021,
      "poster": {
        "url": "https://st.kp.yandex.net/images/film_big/1009142.jpg",
        "previewUrl": "https://st.kp.yandex.net/images/film_iphone/iphone360_1009142.jpg"
      },
      "genres": [
        {
          "name": "\u043c\u0443\u043b\u044c\u0442\u0444\u0438\u043b\u044c\u043c"
        },
        {
          "name": "\u043c\u044e\u0437\u0438\u043a\u043b"
        },
        {
          "name": "\u043a\u043e\u043c\u0435\u0434\u0438\u044f"
        },
        {
          "name": "\u043f\u0440\u0438\u043a\u043b\u044e\u0447\u0435\u043d\u0438\u044f"
        },
        {
          "name": "\u0441\u0435\u043c\u0435\u0439\u043d\u044b\u0439"
        }
      ],
      "countries": [
        {
          "name": "\u0421\u0428\u0410"
        },
        {
          "name": "\u042f\u043f\u043e\u043d\u0438\u044f"
        }
      ],
      "alternativeName": "Sing 2",
      "enName": null,
      "names": [
        {
          "name": "\u0417\u0432\u0435\u0440\u043e\u043f\u043e\u0439 2"
        },
        {
          "name": "Sing 2"
        },
        {
          "name": "\uc53d 2",
          "language": "KR",
          "type": null
        },
        {
          "name": "\u6b22\u4e50\u597d\u58f0\u97f32",
          "language": "CN",
          "type": "\u559c\u5267 / \u52a8\u753b / \u97f3\u4e50 / \u5947\u5e7b"
        },
        {
          "name": "\u661f\u5922\u52d5\u7269\u5712 2",
          "language": "HK",
          "type": "\u559c\u5287 / \u52d5\u756b / \u97f3\u6a02 / \u5947\u5e7b"
        },
        {
          "name": "\u6b61\u6a02\u597d\u8072\u97f32",
          "language": "TW",
          "type": "\u559c\u5287 / \u52d5\u756b / \u97f3\u6a02 / \u5947\u5e7b"
        },
        {
          "name": "Cantar! 2",
          "language": "PT",
          "type": null
        },
        {
          "name": "Sing 2 - Die Show deines Lebens",
          "language": "DE",
          "type": null
        },
        {
          "name": "Tous en sc\u00e8ne 2",
          "language": "FR",
          "type": null
        },
        {
          "name": "Dziedi! 2",
          "language": "LV",
          "type": null
        },
        {
          "name": "\u0e23\u0e49\u0e2d\u0e07\u0e08\u0e23\u0e34\u0e07 \u0e40\u0e2a\u0e35\u0e22\u0e07\u0e08\u0e23\u0e34\u0e07 2",
          "language": "TH",
          "type": null
        },
        {
          "name": "Syng 2",
          "language": "NO",
          "type": null
        },
        {
          "name": "\u00a1Canta! 2",
          "language": "ES",
          "type": null
        },
        {
          "name": "\u661f\u5922\u52d5\u7269\u57122",
          "language": "HK",
          "type": null
        },
        {
          "name": "SING/\u30b7\u30f3\u30b0: \u30cd\u30af\u30b9\u30c8\u30b9\u30c6\u30fc\u30b8",
          "language": "JP",
          "type": "\u559c\u5287 / \u97f3\u697d"
        },
        {
          "name": "\u10e1\u10d8\u10db\u10e6\u10d4\u10e0\u10d0 2",
          "language": "GE",
          "type": null
        },
        {
          "name": "\uc53d2\uac8c\ub354",
          "language": "KR",
          "type": null
        },
        {
          "name": "Laula 2",
          "language": "EE",
          "type": null
        }
      ],
      "shortDescription": "\u0422\u043e\u043b\u044c\u043a\u043e \u0440\u043e\u043a\u0435\u0440-\u043e\u0442\u0448\u0435\u043b\u044c\u043d\u0438\u043a \u043c\u043e\u0436\u0435\u0442 \u0441\u043f\u0430\u0441\u0442\u0438 \u0433\u0440\u0443\u043f\u043f\u0443 \u0411\u0430\u0441\u0442\u0435\u0440\u0430 \u041c\u0443\u043d\u0430 \u043e\u0442 \u043f\u0440\u043e\u0432\u0430\u043b\u0430. \u0421\u0438\u043a\u0432\u0435\u043b \u043c\u044e\u0437\u0438\u043a\u043b\u0430 \u043f\u0440\u043e \u0436\u0438\u0432\u043e\u0442\u043d\u044b\u0445-\u043c\u0443\u0437\u044b\u043a\u0430\u043d\u0442\u043e\u0432",
      "logo": {
        "url": "https://avatars.mds.yandex.net/get-ott/2419418/2a0000017e79fd43f87dffc52f4e39f587f7/orig"
      },
      "watchability": {
        "items": [
          {
            "name": "Okko",
            "logo": {
              "url": "https://avatars.mds.yandex.net/get-ott/239697/7713e586-17d1-42d1-ac62-53e9ef1e70c3/orig"
            },
            "url": "https://okko.tv/movie/sing-2?utm_medium=referral&utm_source=yandex_search&utm_campaign=new_search_feed"
          },
          {
            "name": "\u0418\u0432\u0438",
            "logo": {
              "url": "https://avatars.mds.yandex.net/get-ott/2419418/0dfd1724-848f-4725-9160-abc571f41c11/orig"
            },
            "url": "https://www.ivi.ru/watch/187153?utm_source=yandex&utm_medium=wizard"
          },
          {
            "name": "PREMIER",
            "logo": {
              "url": "https://avatars.mds.yandex.net/get-ott/239697/0f86e907-9531-47e9-87bd-5101a08d4e30/orig"
            },
            "url": "https://premier.one/show/18838?utm_source=yandex&utm_medium=yandex_feed_search&utm_campaign=yandex_feed"
          },
          {
            "name": "Wink",
            "logo": {
              "url": "https://avatars.mds.yandex.net/get-ott/1672343/54096cbe-cc3b-41c9-8e44-990ebbca8d61/orig"
            },
            "url": "https://wink.ru/media_items/137038099?utm_source=yandex&utm_medium=koldunschick&utm_content=name"
          },
          {
            "name": "viju",
            "logo": {
              "url": "https://avatars.mds.yandex.net/get-ott/224348/8b10c84b-e1bb-4493-9bc4-6ee56554403a/orig"
            },
            "url": "https://viju.ru/filmy/zveropoy-2?utm_campaign=yandex_content_integration&utm_medium=affiliate&utm_source=yandex"
          },
          {
            "name": "\u041d\u0422\u0412-\u041f\u041b\u042e\u0421 \u041e\u043d\u043b\u0430\u0439\u043d \u0422\u0412",
            "logo": {
              "url": "https://avatars.mds.yandex.net/get-ott/223007/c6b9b3d8-3258-4394-9cae-c86fdb56a0c6/orig"
            },
            "url": "https://ntvplus.tv/watch/23238-zveropoj-2?utm_source=kinopoisk"
          },
          {
            "name": "24\u0422\u0412",
            "logo": {
              "url": "https://avatars.mds.yandex.net/get-ott/2439731/85e83b8d-1159-4781-bad5-ce0a809b3843/orig"
            },
            "url": "https://24h.tv/contents/2021-sing-2-694594485071357466"
          }
        ]
      }
    },
    {
      "externalId": {
        "kpHD": "457d02b3596858888f563f72e3d12b4b",
        "imdb": "tt0415481",
        "tmdb": 33065
      },
      "rating": {
        "kp": 7.755,
        "imdb": 7.1,
        "filmCritics": 0,
        "russianFilmCritics": 0,
        "await": null
      },
      "votes": {
        "kp": 254320,
        "imdb": 3134,
        "filmCritics": 0,
        "russianFilmCritics": 0,
        "await": 0
      },
      "movieLength": 79,
      "id": 81041,
      "type": "cartoon",
      "name": "\u0410\u043b\u0435\u0448\u0430 \u041f\u043e\u043f\u043e\u0432\u0438\u0447 \u0438 \u0422\u0443\u0433\u0430\u0440\u0438\u043d \u0417\u043c\u0435\u0439",
      "description": "\u041a\u043e\u0433\u0434\u0430 \u043f\u043e\u0434\u0441\u0442\u0443\u043f\u0438\u043b\u0430 \u043a \u0420\u043e\u0441\u0442\u043e\u0432\u0443 \u0432\u0440\u0430\u0436\u0435\u0441\u043a\u0430\u044f \u043e\u0440\u0434\u0430 \u0432\u043e \u0433\u043b\u0430\u0432\u0435 \u0441 \u0422\u0443\u0433\u0430\u0440\u0438\u043d\u044b\u043c \u0417\u043c\u0435\u0435\u043c, \u0410\u043b\u0435\u0448\u0430 \u041f\u043e\u043f\u043e\u0432\u0438\u0447 \u043d\u0435 \u0441\u0443\u043c\u0435\u043b \u0443\u0431\u0435\u0440\u0435\u0447\u044c \u0436\u0438\u0442\u0435\u043b\u0435\u0439 \u043e\u0442 \u0432\u044b\u043f\u043b\u0430\u0442\u044b \u0434\u0430\u043d\u0438. \u0422\u0435\u043f\u0435\u0440\u044c \u0431\u043e\u0433\u0430\u0442\u044b\u0440\u044c \u0434\u043e\u043b\u0436\u0435\u043d \u0432\u043e\u0441\u0441\u0442\u0430\u043d\u043e\u0432\u0438\u0442\u044c \u0434\u043e\u0431\u0440\u043e\u0435 \u0438\u043c\u044f, \u0432\u0435\u0440\u043d\u0443\u0442\u044c \u0437\u043e\u043b\u043e\u0442\u043e \u0438 \u043f\u0440\u043e\u0433\u043d\u0430\u0442\u044c \u043d\u0435\u043f\u0440\u0438\u044f\u0442\u0435\u043b\u044f \u0441 \u0437\u0435\u043c\u043b\u0438 \u0440\u0443\u0441\u0441\u043a\u043e\u0439. \u041e\u043d \u043e\u0442\u043f\u0440\u0430\u0432\u043b\u044f\u0435\u0442\u0441\u044f \u0432 \u043f\u0443\u0442\u0435\u0448\u0435\u0441\u0442\u0432\u0438\u0435, \u0430 \u043f\u043e\u043c\u043e\u0433\u0443\u0442 \u0435\u043c\u0443 \u0432 \u044d\u0442\u043e\u043c \u0434\u044f\u0434\u044c\u043a\u0430 \u0422\u0438\u0445\u043e\u043d, \u0434\u0435\u0432\u0443\u0448\u043a\u0430 \u041b\u044e\u0431\u0430\u0432\u0430, \u0435\u0435 \u0431\u0430\u0431\u0443\u0448\u043a\u0430 \u0438 \u0433\u043e\u0432\u043e\u0440\u044f\u0449\u0438\u0439 \u043a\u043e\u043d\u044c \u042e\u043b\u0438\u0439.",
      "year": 2004,
      "poster": {
        "url": "https://st.kp.yandex.net/images/film_big/81041.jpg",
        "previewUrl": "https://st.kp.yandex.net/images/film_iphone/iphone360_81041.jpg"
      },
      "genres": [
        {
          "name": "\u043c\u0443\u043b\u044c\u0442\u0444\u0438\u043b\u044c\u043c"
        },
        {
          "name": "\u043a\u043e\u043c\u0435\u0434\u0438\u044f"
        },
        {
          "name": "\u043f\u0440\u0438\u043a\u043b\u044e\u0447\u0435\u043d\u0438\u044f"
        },
        {
          "name": "\u043c\u044e\u0437\u0438\u043a\u043b"
        },
        {
          "name": "\u0444\u044d\u043d\u0442\u0435\u0437\u0438"
        },
        {
          "name": "\u043c\u0435\u043b\u043e\u0434\u0440\u0430\u043c\u0430"
        },
        {
          "name": "\u0441\u0435\u043c\u0435\u0439\u043d\u044b\u0439"
        }
      ],
      "countries": [
        {
          "name": "\u0420\u043e\u0441\u0441\u0438\u044f"
        }
      ],
      "alternativeName": null,
      "enName": null,
      "names": [
        {
          "name": "\u0410\u043b\u0435\u0448\u0430 \u041f\u043e\u043f\u043e\u0432\u0438\u0447 \u0438 \u0422\u0443\u0433\u0430\u0440\u0438\u043d \u0417\u043c\u0435\u0439"
        }
      ],
      "shortDescription": "\u041f\u043e\u043f\u043e\u0432\u0441\u043a\u0438\u0439 \u0441\u044b\u043d \u0441\u043b\u044b\u0432\u0435\u0442 \u043d\u0435\u0434\u043e\u0442\u0435\u043f\u043e\u0439, \u043d\u043e \u0441\u0432\u043e\u0439 \u0433\u043e\u0440\u043e\u0434 \u043e\u043d \u0432 \u043e\u0431\u0438\u0434\u0443 \u043d\u0435 \u0434\u0430\u0441\u0442. \u041f\u0435\u0440\u0432\u043e\u0435 \u0437\u043d\u0430\u043a\u043e\u043c\u0441\u0442\u0432\u043e \u0441 \u0432\u0435\u0441\u0435\u043b\u044b\u043c \u043c\u0438\u0440\u043e\u043c \u0431\u043e\u0433\u0430\u0442\u044b\u0440\u0435\u0439",
      "logo": {
        "url": "https://avatars.mds.yandex.net/get-ott/1534341/2a0000016ef5806e4c011e98833861b1a745/orig"
      },
      "watchability": {
        "items": [
          {
            "name": "Okko",
            "logo": {
              "url": "https://avatars.mds.yandex.net/get-ott/239697/7713e586-17d1-42d1-ac62-53e9ef1e70c3/orig"
            },
            "url": "https://okko.tv/movie/alesha-popovich-i-tugarin-zmejj?utm_medium=referral&utm_source=yandex_search&utm_campaign=new_search_feed"
          },
          {
            "name": "\u0418\u0432\u0438",
            "logo": {
              "url": "https://avatars.mds.yandex.net/get-ott/2419418/0dfd1724-848f-4725-9160-abc571f41c11/orig"
            },
            "url": "https://www.ivi.ru/watch/33529?utm_source=yandex&utm_medium=wizard"
          },
          {
            "name": "KION",
            "logo": {
              "url": "https://avatars.mds.yandex.net/get-ott/239697/daeb142e-3ecc-4bb2-9bff-4827996643ab/orig"
            },
            "url": "https://kion.ru/video/movie/284616655?utm_source=yandex&utm_medium=organic&utm_campaign=wizard"
          },
          {
            "name": "PREMIER",
            "logo": {
              "url": "https://avatars.mds.yandex.net/get-ott/239697/0f86e907-9531-47e9-87bd-5101a08d4e30/orig"
            },
            "url": "https://premier.one/show/9690?utm_source=yandex&utm_medium=yandex_feed_search&utm_campaign=yandex_feed"
          },
          {
            "name": "more.tv",
            "logo": {
              "url": "https://avatars.mds.yandex.net/get-ott/1648503/97e3cbbd-40ee-4298-888d-ed2d0f022a69/orig"
            },
            "url": "https://more.tv/alyesha-popovich-i-tugarin-zmey?utm_source=yandex-snippet&utm_medium=snippet&utm_campaign=alesha_popovich_i_tugarin_zmei"
          },
          {
            "name": "Wink",
            "logo": {
              "url": "https://avatars.mds.yandex.net/get-ott/1672343/54096cbe-cc3b-41c9-8e44-990ebbca8d61/orig"
            },
            "url": "https://wink.ru/media_items/70753295?utm_source=yandex&utm_medium=koldunschick&utm_content=name"
          },
          {
            "name": "\u0421\u043c\u043e\u0442\u0440\u0451\u0448\u043a\u0430",
            "logo": {
              "url": "https://avatars.mds.yandex.net/get-ott/236744/c88e652e-2eb1-472d-b636-a266364dbf58/orig"
            },
            "url": "https://smotreshka.tv/archive/5b22457921887f17428ba73b?utm_source=yandex_search&utm_campaign=yandex_feed&utm_content=archiv_april"
          },
          {
            "name": "24\u0422\u0412",
            "logo": {
              "url": "https://avatars.mds.yandex.net/get-ott/2439731/85e83b8d-1159-4781-bad5-ce0a809b3843/orig"
            },
            "url": "https://24h.tv/contents/2004-alyosha-popovich-and-tugar-546309356648399159"
          }
        ]
      }
    },
    {
      "externalId": {
        "kpHD": "46c7a2cb287af5dcb47cbb0e0c0bcc7d",
        "imdb": "tt0121164",
        "tmdb": 3933
      },
      "rating": {
        "kp": 7.85,
        "imdb": 7.3,
        "filmCritics": 7.2,
        "russianFilmCritics": 0,
        "await": null
      },
      "votes": {
        "kp": 238402,
        "imdb": 282987,
        "filmCritics": 197,
        "russianFilmCritics": 1,
        "await": 0
      },
      "movieLength": 77,
      "id": 77548,
      "type": "cartoon",
      "name": "\u0422\u0440\u0443\u043f \u043d\u0435\u0432\u0435\u0441\u0442\u044b",
      "description": "\u0414\u0435\u0439\u0441\u0442\u0432\u0438\u0435 \u0440\u0430\u0437\u0432\u0438\u0432\u0430\u0435\u0442\u0441\u044f \u0432 \u0435\u0432\u0440\u043e\u043f\u0435\u0439\u0441\u043a\u043e\u0439 \u0434\u0435\u0440\u0435\u0432\u0443\u0448\u043a\u0435 XIX \u0432\u0435\u043a\u0430. \u0413\u043b\u0430\u0432\u043d\u043e\u0433\u043e \u0433\u0435\u0440\u043e\u044f \u2013 \u043c\u043e\u043b\u043e\u0434\u043e\u0433\u043e \u0447\u0435\u043b\u043e\u0432\u0435\u043a\u0430 \u0412\u0438\u043a\u0442\u043e\u0440\u0430 \u2013 \u0441\u0438\u043b\u044b \u0442\u044c\u043c\u044b \u0443\u0442\u0430\u0441\u043a\u0438\u0432\u0430\u044e\u0442 \u0432 \u043f\u0440\u0435\u0438\u0441\u043f\u043e\u0434\u043d\u044e\u044e \u0438 \u0436\u0435\u043d\u044f\u0442 \u0442\u0430\u043c \u043d\u0430 \u0442\u0430\u0438\u043d\u0441\u0442\u0432\u0435\u043d\u043d\u043e\u043c \u0422\u0440\u0443\u043f\u0435 \u041d\u0435\u0432\u0435\u0441\u0442\u044b, \u0432 \u0442\u043e \u0432\u0440\u0435\u043c\u044f \u043a\u0430\u043a \u0435\u0433\u043e \u043d\u0430\u0441\u0442\u043e\u044f\u0449\u0430\u044f \u043d\u0435\u0432\u0435\u0441\u0442\u0430 \u0412\u0438\u043a\u0442\u043e\u0440\u0438\u044f \u043e\u0436\u0438\u0434\u0430\u0435\u0442 \u0441\u0432\u043e\u0435\u0433\u043e \u0436\u0435\u043d\u0438\u0445\u0430 \u0432 \u043c\u0438\u0440\u0435 \u0436\u0438\u0432\u044b\u0445.\u041d\u0435\u0441\u043c\u043e\u0442\u0440\u044f \u043d\u0430 \u0442\u043e, \u0447\u0442\u043e \u043f\u0440\u043e\u0436\u0438\u0432\u0430\u043d\u0438\u0435 \u0432 \u0426\u0430\u0440\u0441\u0442\u0432\u0435 \u043c\u0435\u0440\u0442\u0432\u044b\u0445 \u043e\u043a\u0430\u0437\u044b\u0432\u0430\u0435\u0442\u0441\u044f \u043c\u043d\u043e\u0433\u043e \u0438\u043d\u0442\u0435\u0440\u0435\u0441\u043d\u0435\u0439, \u0447\u0435\u043c \u0435\u0433\u043e \u043f\u0440\u0438\u0432\u044b\u0447\u043d\u044b\u0439 \u0432\u0438\u043a\u0442\u043e\u0440\u0438\u0430\u043d\u0441\u043a\u0438\u0439 \u043e\u0431\u0440\u0430\u0437 \u0436\u0438\u0437\u043d\u0438, \u0412\u0438\u043a\u0442\u043e\u0440 \u043f\u043e\u043d\u0438\u043c\u0430\u0435\u0442, \u0447\u0442\u043e \u0441\u0432\u043e\u044e \u0435\u0434\u0438\u043d\u0441\u0442\u0432\u0435\u043d\u043d\u0443\u044e \u043b\u044e\u0431\u043e\u0432\u044c \u043e\u043d \u043d\u0435 \u043f\u0440\u043e\u043c\u0435\u043d\u044f\u0435\u0442 \u043d\u0438 \u043d\u0430 \u0447\u0442\u043e \u043d\u0438 \u0432 \u043e\u0434\u043d\u043e\u043c \u0438\u0437 \u0430\u043b\u044c\u0442\u0435\u0440\u043d\u0430\u0442\u0438\u0432\u043d\u044b\u0445 \u043c\u0438\u0440\u043e\u0432\u2026",
      "year": 2005,
      "poster": {
        "url": "https://st.kp.yandex.net/images/film_big/77548.jpg",
        "previewUrl": "https://st.kp.yandex.net/images/film_iphone/iphone360_77548.jpg"
      },
      "genres": [
        {
          "name": "\u043c\u0443\u043b\u044c\u0442\u0444\u0438\u043b\u044c\u043c"
        },
        {
          "name": "\u043c\u044e\u0437\u0438\u043a\u043b"
        },
        {
          "name": "\u0444\u044d\u043d\u0442\u0435\u0437\u0438"
        },
        {
          "name": "\u0434\u0440\u0430\u043c\u0430"
        },
        {
          "name": "\u043c\u0435\u043b\u043e\u0434\u0440\u0430\u043c\u0430"
        },
        {
          "name": "\u0441\u0435\u043c\u0435\u0439\u043d\u044b\u0439"
        }
      ],
      "countries": [
        {
          "name": "\u0421\u0428\u0410"
        },
        {
          "name": "\u0412\u0435\u043b\u0438\u043a\u043e\u0431\u0440\u0438\u0442\u0430\u043d\u0438\u044f"
        }
      ],
      "alternativeName": "Corpse Bride",
      "enName": null,
      "names": [
        {
          "name": "\u0422\u0440\u0443\u043f \u043d\u0435\u0432\u0435\u0441\u0442\u044b"
        },
        {
          "name": "Corpse Bride"
        },
        {
          "name": "La Mari\u00e9e cadav\u00e9rique",
          "language": "CA",
          "type": null
        },
        {
          "name": "Tim Burton's Corpse Bride",
          "language": "US",
          "type": null
        },
        {
          "name": "Les noces fun\u00e8bres de Tim Burton",
          "language": "BE",
          "type": null
        },
        {
          "name": "Laibast pruut",
          "language": "EE",
          "type": null
        },
        {
          "name": "Gnijaca panna mloda",
          "language": "PL",
          "type": null
        },
        {
          "name": "Mrtva nevjesta",
          "language": "HR",
          "type": null
        },
        {
          "name": "Cosmar inainte de Craciun",
          "language": "RO",
          "type": null
        },
        {
          "name": "Mrtva nevesta",
          "language": "SI",
          "type": null
        },
        {
          "name": "Andregai hilotza",
          "language": "ES",
          "type": "Euskera"
        },
        {
          "name": "M\u0155tva nevesta Tima Burtona",
          "language": "SK",
          "type": null
        },
        {
          "name": "\u0639\u0631\u0648\u0633 \u0645\u0631\u062f\u0647",
          "language": "IR",
          "type": null
        },
        {
          "name": "\u602a\u8bde\u5c38\u65b0\u5a18",
          "language": "CN",
          "type": null
        }
      ],
      "shortDescription": "\u0416\u0435\u043d\u0438\u0445 \u043d\u0430\u043a\u0430\u043d\u0443\u043d\u0435 \u0432\u0435\u043d\u0447\u0430\u043d\u0438\u044f \u043f\u043e\u043f\u0430\u0434\u0430\u0435\u0442 \u0432 \u043c\u0438\u0440 \u043c\u0435\u0440\u0442\u0432\u044b\u0445. \u041c\u0443\u043b\u044c\u0442\u0444\u0438\u043b\u044c\u043c \u0422\u0438\u043c\u0430 \u0411\u0451\u0440\u0442\u043e\u043d\u0430 \u0441 \u0438\u0437\u044b\u0441\u043a\u0430\u043d\u043d\u043e\u0439 \u043a\u0443\u043a\u043e\u043b\u044c\u043d\u043e\u0439 \u0430\u043d\u0438\u043c\u0430\u0446\u0438\u0435\u0439",
      "logo": {
        "url": "https://avatars.mds.yandex.net/get-ott/2439731/2a000001726fc56aa475c89974ceb66aaebb/orig"
      },
      "watchability": {
        "items": null
      }
    },
    {
      "externalId": {
        "kpHD": "425c1a4fcd293a91a3b059436ab48433",
        "imdb": "tt3470600",
        "tmdb": 335797
      },
      "rating": {
        "kp": 7.376,
        "imdb": 7.1,
        "filmCritics": 6.4,
        "russianFilmCritics": 100,
        "await": null
      },
      "votes": {
        "kp": 229398,
        "imdb": 177684,
        "filmCritics": 189,
        "russianFilmCritics": 9,
        "await": 7208
      },
      "movieLength": 108,
      "id": 821008,
      "type": "cartoon",
      "name": "\u0417\u0432\u0435\u0440\u043e\u043f\u043e\u0439",
      "description": "\u0412 \u043c\u0438\u0440\u0435, \u043a\u043e\u0442\u043e\u0440\u044b\u0439 \u043d\u0430\u0441\u0435\u043b\u044f\u044e\u0442 \u0437\u0432\u0435\u0440\u0438, \u043a\u043e\u0430\u043b\u0430 \u043f\u043e \u0438\u043c\u0435\u043d\u0438 \u0411\u0430\u0441\u0442\u0435\u0440 \u041c\u0443\u043d \u0438\u0437\u043e \u0432\u0441\u0435\u0445 \u0441\u0438\u043b \u043f\u044b\u0442\u0430\u0435\u0442\u0441\u044f \u043f\u0440\u0435\u0434\u043e\u0442\u0432\u0440\u0430\u0442\u0438\u0442\u044c \u0437\u0430\u043a\u0440\u044b\u0442\u0438\u0435 \u0441\u0432\u043e\u0435\u0433\u043e \u0442\u0435\u0430\u0442\u0440\u0430. \u0412 \u0438\u0442\u043e\u0433\u0435 \u0411\u0430\u0441\u0442\u0435\u0440 \u0438 \u0435\u0433\u043e \u0434\u0440\u0443\u0433 \u0431\u0430\u0440\u0430\u043d \u042d\u0434\u0434\u0438 \u0443\u0441\u0442\u0440\u0430\u0438\u0432\u0430\u044e\u0442 \u043a\u043e\u043d\u043a\u0443\u0440\u0441 \u043f\u0435\u0432\u0446\u043e\u0432, \u043f\u0440\u0435\u0434\u043b\u0430\u0433\u0430\u044f \u043f\u0440\u0438\u043d\u044f\u0442\u044c \u0443\u0447\u0430\u0441\u0442\u0438\u0435 \u043a\u0430\u0436\u0434\u043e\u043c\u0443 \u0436\u0438\u0442\u0435\u043b\u044e \u0433\u043e\u0440\u043e\u0434\u0430.",
      "year": 2016,
      "poster": {
        "url": "https://st.kp.yandex.net/images/film_big/821008.jpg",
        "previewUrl": "https://st.kp.yandex.net/images/film_iphone/iphone360_821008.jpg"
      },
      "genres": [
        {
          "name": "\u043c\u0443\u043b\u044c\u0442\u0444\u0438\u043b\u044c\u043c"
        },
        {
          "name": "\u043c\u044e\u0437\u0438\u043a\u043b"
        },
        {
          "name": "\u043a\u043e\u043c\u0435\u0434\u0438\u044f"
        },
        {
          "name": "\u0441\u0435\u043c\u0435\u0439\u043d\u044b\u0439"
        }
      ],
      "countries": [
        {
          "name": "\u042f\u043f\u043e\u043d\u0438\u044f"
        },
        {
          "name": "\u0421\u0428\u0410"
        },
        {
          "name": "\u0424\u0440\u0430\u043d\u0446\u0438\u044f"
        }
      ],
      "alternativeName": "Sing",
      "enName": null,
      "names": [
        {
          "name": "\u0417\u0432\u0435\u0440\u043e\u043f\u043e\u0439"
        },
        {
          "name": "Sing"
        }
      ],
      "shortDescription": "\u0421\u043f\u0430\u0441\u0430\u044f \u0442\u0435\u0430\u0442\u0440 \u043e\u0442 \u0437\u0430\u043a\u0440\u044b\u0442\u0438\u044f, \u043a\u043e\u0430\u043b\u0430 \u0411\u0430\u0441\u0442\u0435\u0440 \u041c\u0443\u043d \u043e\u0442\u043a\u0440\u044b\u0432\u0430\u0435\u0442 \u043d\u043e\u0432\u044b\u0435 \u0442\u0430\u043b\u0430\u043d\u0442\u044b. \u0420\u0430\u0437\u043d\u043e\u0448\u0435\u0440\u0441\u0442\u043d\u044b\u0435 \u0430\u0440\u0442\u0438\u0441\u0442\u044b \u0438 \u043f\u043e\u0447\u0442\u0438 \u0441\u043e\u0442\u043d\u044f \u0445\u0438\u0442\u043e\u0432",
      "logo": {
        "url": "https://avatars.mds.yandex.net/get-ott/2439731/2a000001720d26999e1d743f9b7216d2c819/orig"
      },
      "watchability": {
        "items": [
          {
            "name": "Okko",
            "logo": {
              "url": "https://avatars.mds.yandex.net/get-ott/239697/7713e586-17d1-42d1-ac62-53e9ef1e70c3/orig"
            },
            "url": "https://okko.tv/movie/sing?utm_medium=referral&utm_source=yandex_search&utm_campaign=new_search_feed"
          },
          {
            "name": "\u0418\u0432\u0438",
            "logo": {
              "url": "https://avatars.mds.yandex.net/get-ott/2419418/0dfd1724-848f-4725-9160-abc571f41c11/orig"
            },
            "url": "https://www.ivi.ru/watch/133311?utm_source=yandex&utm_medium=wizard"
          },
          {
            "name": "Wink",
            "logo": {
              "url": "https://avatars.mds.yandex.net/get-ott/1672343/54096cbe-cc3b-41c9-8e44-990ebbca8d61/orig"
            },
            "url": "https://wink.ru/media_items/54783123?utm_source=yandex&utm_medium=koldunschick&utm_content=name"
          },
          {
            "name": "viju",
            "logo": {
              "url": "https://avatars.mds.yandex.net/get-ott/224348/8b10c84b-e1bb-4493-9bc4-6ee56554403a/orig"
            },
            "url": "https://viju.ru/filmy/zveropoy?utm_campaign=yandex_content_integration&utm_medium=affiliate&utm_source=yandex"
          },
          {
            "name": "\u041d\u0422\u0412-\u041f\u041b\u042e\u0421 \u041e\u043d\u043b\u0430\u0439\u043d \u0422\u0412",
            "logo": {
              "url": "https://avatars.mds.yandex.net/get-ott/223007/c6b9b3d8-3258-4394-9cae-c86fdb56a0c6/orig"
            },
            "url": "https://ntvplus.tv/watch/25532-zveropoj?utm_source=kinopoisk"
          },
          {
            "name": "24\u0422\u0412",
            "logo": {
              "url": "https://avatars.mds.yandex.net/get-ott/2439731/85e83b8d-1159-4781-bad5-ce0a809b3843/orig"
            },
            "url": "https://24h.tv/contents/2016-sing-546325404625929067"
          }
        ]
      }
    },
    {
      "externalId": {
        "kpHD": "4038727c0f3f6d65a5e74f5df3677371",
        "imdb": "tt0097757",
        "tmdb": 10144
      },
      "rating": {
        "kp": 8.203,
        "imdb": 7.6,
        "filmCritics": 8.2,
        "russianFilmCritics": 0,
        "await": null
      },
      "votes": {
        "kp": 211948,
        "imdb": 271486,
        "filmCritics": 72,
        "russianFilmCritics": 0,
        "await": 0
      },
      "movieLength": 83,
      "id": 8147,
      "type": "cartoon",
      "name": "\u0420\u0443\u0441\u0430\u043b\u043e\u0447\u043a\u0430",
      "description": "\u0422\u0430\u0438\u043d\u0441\u0442\u0432\u0435\u043d\u043d\u044b\u0435 \u0433\u043b\u0443\u0431\u0438\u043d\u044b \u043c\u043e\u0440\u044f \u0445\u0440\u0430\u043d\u044f\u0442 \u043d\u0435\u043c\u0430\u043b\u043e \u0442\u0430\u0439\u043d, \u0430 \u043e\u0431\u0438\u0442\u0430\u0442\u0435\u043b\u0438 \u043e\u043a\u0435\u0430\u043d\u0430 \u043c\u043e\u0433\u0443\u0442 \u0440\u0430\u0441\u0441\u043a\u0430\u0437\u0430\u0442\u044c \u043c\u043d\u043e\u0436\u0435\u0441\u0442\u0432\u043e \u0443\u0434\u0438\u0432\u0438\u0442\u0435\u043b\u044c\u043d\u044b\u0445 \u0438\u0441\u0442\u043e\u0440\u0438\u0439. \u0418 \u0441\u0430\u043c\u043e\u0439 \u043d\u0435\u0432\u0435\u0440\u043e\u044f\u0442\u043d\u043e\u0439 \u0438\u0437 \u043d\u0438\u0445 \u0431\u044b\u043b\u0430 \u0438 \u043e\u0441\u0442\u0430\u0451\u0442\u0441\u044f \u0438\u0441\u0442\u043e\u0440\u0438\u044f \u0440\u0443\u0441\u0430\u043b\u043e\u0447\u043a\u0438 \u0410\u0440\u0438\u044d\u043b\u044c. \u0414\u043e\u0447\u044c \u043c\u043e\u0433\u0443\u0449\u0435\u0441\u0442\u0432\u0435\u043d\u043d\u043e\u0433\u043e \u0446\u0430\u0440\u044f \u043f\u043e\u0434\u0432\u043e\u0434\u043d\u043e\u0433\u043e \u043c\u0438\u0440\u0430 \u0422\u0440\u0438\u0442\u043e\u043d\u0430, \u043e\u043d\u0430 \u043e\u0434\u043d\u0430\u0436\u0434\u044b \u0432\u043b\u044e\u0431\u043b\u044f\u0435\u0442\u0441\u044f \u0432 \u043f\u0440\u0435\u043a\u0440\u0430\u0441\u043d\u043e\u0433\u043e \u0438 \u043c\u0443\u0436\u0435\u0441\u0442\u0432\u0435\u043d\u043d\u043e\u0433\u043e \u043f\u0440\u0438\u043d\u0446\u0430. \u041d\u043e \u0440\u0430\u0437\u0432\u0435 \u043e\u043d\u0438 \u043c\u043e\u0433\u0443\u0442 \u0431\u044b\u0442\u044c \u0432\u043c\u0435\u0441\u0442\u0435 - \u0437\u0435\u043c\u043d\u043e\u0439 \u0447\u0435\u043b\u043e\u0432\u0435\u043a \u0438 \u043c\u043e\u0440\u0441\u043a\u0430\u044f \u0434\u0435\u0432\u0430? \u041e\u0434\u043d\u0430\u043a\u043e \u043d\u0430\u0441\u0442\u043e\u044f\u0449\u0438\u0435 \u0447\u0443\u0432\u0441\u0442\u0432\u0430 \u043f\u0440\u0435\u043e\u0434\u043e\u043b\u0435\u0432\u0430\u044e\u0442 \u043b\u044e\u0431\u044b\u0435 \u043f\u0440\u0435\u0433\u0440\u0430\u0434\u044b. \u0420\u0430\u0434\u0438 \u0441\u0432\u043e\u0435\u0439 \u043b\u044e\u0431\u0432\u0438 \u0410\u0440\u0438\u044d\u043b\u044c \u0433\u043e\u0442\u043e\u0432\u0430 \u043f\u043e\u0439\u0442\u0438 \u043d\u0430 \u0432\u0441\u0451. \u0414\u0430\u0436\u0435 \u0435\u0441\u043b\u0438 \u0434\u043b\u044f \u043e\u0431\u0440\u0435\u0442\u0435\u043d\u0438\u044f \u0441\u0432\u043e\u0435\u0433\u043e \u0441\u0447\u0430\u0441\u0442\u044c\u044f \u0435\u0439 \u043d\u0430\u0432\u0441\u0435\u0433\u0434\u0430 \u043f\u0440\u0438\u0434\u0451\u0442\u0441\u044f \u043f\u043e\u043a\u0438\u043d\u0443\u0442\u044c \u0440\u043e\u0434\u043d\u043e\u0439 \u043e\u043a\u0435\u0430\u043d \u0438 \u043d\u0430\u0432\u0435\u043a\u0438 \u0441\u0442\u0430\u0442\u044c \u0437\u0435\u043c\u043d\u043e\u0439 \u0434\u0435\u0432\u0443\u0448\u043a\u043e\u0439...",
      "year": 1989,
      "poster": {
        "url": "https://st.kp.yandex.net/images/film_big/8147.jpg",
        "previewUrl": "https://st.kp.yandex.net/images/film_iphone/iphone360_8147.jpg"
      },
      "genres": [
        {
          "name": "\u043c\u0443\u043b\u044c\u0442\u0444\u0438\u043b\u044c\u043c"
        },
        {
          "name": "\u043c\u044e\u0437\u0438\u043a\u043b"
        },
        {
          "name": "\u0444\u044d\u043d\u0442\u0435\u0437\u0438"
        },
        {
          "name": "\u043c\u0435\u043b\u043e\u0434\u0440\u0430\u043c\u0430"
        },
        {
          "name": "\u043a\u043e\u043c\u0435\u0434\u0438\u044f"
        },
        {
          "name": "\u043f\u0440\u0438\u043a\u043b\u044e\u0447\u0435\u043d\u0438\u044f"
        },
        {
          "name": "\u0441\u0435\u043c\u0435\u0439\u043d\u044b\u0439"
        }
      ],
      "countries": [
        {
          "name": "\u0421\u0428\u0410"
        }
      ],
      "alternativeName": "The Little Mermaid",
      "enName": null,
      "names": [
        {
          "name": "\u0420\u0443\u0441\u0430\u043b\u043e\u0447\u043a\u0430"
        },
        {
          "name": "The Little Mermaid"
        },
        {
          "name": "Litla hafmeyjan",
          "language": "IS",
          "type": null
        },
        {
          "name": "De Kleine Zeemeermin",
          "language": "NL",
          "type": null
        },
        {
          "name": "La Sirenetta 1",
          "language": "IT",
          "type": null
        },
        {
          "name": "La Petite Sir\u00e8ne",
          "language": "FR",
          "type": "Animation"
        },
        {
          "name": "A Pequena Sereia",
          "language": "BR",
          "type": "Anima\u00e7\u00e3o"
        },
        {
          "name": "Little Mermaid 1",
          "language": "US",
          "type": "Series Title"
        },
        {
          "name": "Arielle, die Meerjungfrau",
          "language": "DE",
          "type": null
        }
      ],
      "shortDescription": "\u0420\u044b\u0436\u0435\u0432\u043e\u043b\u043e\u0441\u0430\u044f \u0410\u0440\u0438\u044d\u043b\u044c \u043c\u0435\u0447\u0442\u0430\u0435\u0442 \u0441\u0442\u0430\u0442\u044c \u0447\u0435\u043b\u043e\u0432\u0435\u043a\u043e\u043c \u0438 \u0432\u043b\u044e\u0431\u0438\u0442\u044c\u0441\u044f. \u0418\u0441\u0442\u043e\u0440\u0438\u044f \u043f\u0435\u0440\u0435\u0432\u043e\u043f\u043b\u043e\u0449\u0435\u043d\u0438\u044f \u0441 \u043c\u0443\u0437\u044b\u043a\u0430\u043b\u044c\u043d\u044b\u043c\u0438 \u0445\u0438\u0442\u0430\u043c\u0438 Disney",
      "logo": {
        "url": "https://avatars.mds.yandex.net/get-ott/223007/2a0000016ef3a1f39450333afc1f3e808359/orig"
      },
      "watchability": {
        "items": null
      }
    },
    {
      "externalId": {
        "kpHD": "4dfee90ae54b174ebc464665641531f6",
        "imdb": "tt0118617",
        "tmdb": 9444
      },
      "rating": {
        "kp": 8.111,
        "imdb": 7.1,
        "filmCritics": 7.1,
        "russianFilmCritics": 0,
        "await": null
      },
      "votes": {
        "kp": 210790,
        "imdb": 128746,
        "filmCritics": 58,
        "russianFilmCritics": 0,
        "await": 0
      },
      "movieLength": 94,
      "id": 2513,
      "type": "cartoon",
      "name": "\u0410\u043d\u0430\u0441\u0442\u0430\u0441\u0438\u044f",
      "description": "\u0410\u043d\u0430\u0441\u0442\u0430\u0441\u0438\u044f \u2014 \u0434\u043e\u0447\u043a\u0430 \u043f\u043e\u0441\u043b\u0435\u0434\u043d\u0435\u0433\u043e \u0440\u0443\u0441\u0441\u043a\u043e\u0433\u043e \u0446\u0430\u0440\u044f \u041d\u0438\u043a\u043e\u043b\u0430\u044f, \u043f\u043e\u0433\u0443\u0431\u043b\u0435\u043d\u043d\u043e\u0433\u043e \u0437\u043b\u043e\u0432\u0435\u0449\u0438\u043c \u0420\u0430\u0441\u043f\u0443\u0442\u0438\u043d\u044b\u043c. \u0415\u0439 \u0443\u0434\u0430\u0435\u0442\u0441\u044f \u0441\u043f\u0430\u0441\u0442\u0438\u0441\u044c, \u0434\u043e\u0431\u0440\u0430\u0442\u044c\u0441\u044f \u0432\u043c\u0435\u0441\u0442\u0435 \u0441 \u0431\u0430\u0431\u0443\u0448\u043a\u043e\u0439 \u0434\u043e \u043f\u0435\u0440\u0435\u043f\u043e\u043b\u043d\u0435\u043d\u043d\u043e\u0433\u043e \u0432\u043e\u043a\u0437\u0430\u043b\u0430 \u0438\u2026 \u043f\u043e\u0442\u0435\u0440\u044f\u0442\u044c\u0441\u044f \u0432 \u0442\u043e\u043b\u043f\u0435. \u041f\u0440\u043e\u0445\u043e\u0434\u0438\u0442 \u0434\u0435\u0441\u044f\u0442\u044c \u043b\u0435\u0442. \u0410\u043d\u0430\u0441\u0442\u0430\u0441\u0438\u044f \u0441\u0442\u0430\u043b\u0430 \u0432\u0437\u0440\u043e\u0441\u043b\u043e\u0439 \u043a\u0440\u0430\u0441\u0430\u0432\u0438\u0446\u0435\u0439 \u0438 \u0442\u0435\u043f\u0435\u0440\u044c \u0445\u043e\u0447\u0435\u0442 \u043f\u043e\u043f\u0430\u0441\u0442\u044c \u0432 \u041f\u0430\u0440\u0438\u0436. \u0421\u043c\u043e\u0436\u0435\u0442 \u043b\u0438 \u0446\u0430\u0440\u0435\u0432\u043d\u0430 \u043e\u0441\u0443\u0449\u0435\u0441\u0442\u0432\u0438\u0442\u044c \u0437\u0430\u0434\u0443\u043c\u0430\u043d\u043d\u043e\u0435? \u0412\u0435\u0434\u044c \u0420\u0430\u0441\u043f\u0443\u0442\u0438\u043d \u0443\u0436\u0435 \u043f\u043e\u0434\u043d\u044f\u043b\u0441\u044f \u0438\u0437 \u0441\u0432\u043e\u0435\u0439 \u043c\u043e\u0433\u0438\u043b\u044b\u2026",
      "year": 1997,
      "poster": {
        "url": "https://st.kp.yandex.net/images/film_big/2513.jpg",
        "previewUrl": "https://st.kp.yandex.net/images/film_iphone/iphone360_2513.jpg"
      },
      "genres": [
        {
          "name": "\u043c\u0443\u043b\u044c\u0442\u0444\u0438\u043b\u044c\u043c"
        },
        {
          "name": "\u043c\u044e\u0437\u0438\u043a\u043b"
        },
        {
          "name": "\u0444\u044d\u043d\u0442\u0435\u0437\u0438"
        },
        {
          "name": "\u0434\u0440\u0430\u043c\u0430"
        },
        {
          "name": "\u043f\u0440\u0438\u043a\u043b\u044e\u0447\u0435\u043d\u0438\u044f"
        },
        {
          "name": "\u0441\u0435\u043c\u0435\u0439\u043d\u044b\u0439"
        }
      ],
      "countries": [
        {
          "name": "\u0421\u0428\u0410"
        }
      ],
      "alternativeName": "Anastasia",
      "enName": null,
      "names": [
        {
          "name": "\u0410\u043d\u0430\u0441\u0442\u0430\u0441\u0438\u044f"
        },
        {
          "name": "Anastasia"
        },
        {
          "name": "\u30a2\u30ca\u30b9\u30bf\u30b7\u30a2",
          "language": "JP",
          "type": null
        },
        {
          "name": "Anastasia 3D",
          "language": "US",
          "type": "200 theaters in 11-21-2014"
        },
        {
          "name": "Anast\u00e1sia",
          "language": "PT",
          "type": null
        },
        {
          "name": "\uc544\ub098\uc2a4\ud0c0\uc0e4",
          "language": "KR",
          "type": null
        },
        {
          "name": "\u041f\u0440\u0438\u043d\u0446\u0435\u0441\u0430 \u0410\u043d\u0430\u0441\u0442\u0430\u0441\u0438\u044f",
          "language": "BG",
          "type": null
        },
        {
          "name": "Princess Anastasia",
          "language": "GB",
          "type": null
        },
        {
          "name": "Princezn\u00e1 Anast\u00e1zia",
          "language": "SK",
          "type": null
        },
        {
          "name": "Anast\u00e0sia",
          "language": "ES",
          "type": "Catalan title"
        }
      ],
      "shortDescription": "\u0421\u0438\u0440\u043e\u0442\u0430 \u0443\u0437\u043d\u0430\u0435\u0442, \u0447\u0442\u043e \u043e\u043d\u0430 \u2014 \u0434\u043e\u0447\u044c \u0440\u0443\u0441\u0441\u043a\u043e\u0433\u043e \u0438\u043c\u043f\u0435\u0440\u0430\u0442\u043e\u0440\u0430. \u0417\u0430\u0432\u043e\u0440\u0430\u0436\u0438\u0432\u0430\u044e\u0449\u0435 \u043a\u0440\u0430\u0441\u0438\u0432\u044b\u0439 \u043c\u0443\u043b\u044c\u0442\u0444\u0438\u043b\u044c\u043c \u0441 \u0432\u044b\u0434\u0430\u044e\u0449\u0435\u0439\u0441\u044f \u043c\u0443\u0437\u044b\u043a\u043e\u0439",
      "logo": {
        "url": "https://avatars.mds.yandex.net/get-ott/1534341/2a00000176af99e77535664c0e8ffc5ee284/orig"
      },
      "watchability": {
        "items": null
      }
    },
    {
      "externalId": {
        "kpHD": "430d83e8f6e6d40cabeb9aa2c6b5b3f9",
        "imdb": "tt0211281",
        "tmdb": 33108
      },
      "rating": {
        "kp": 8.29,
        "imdb": 7.9,
        "filmCritics": 0,
        "russianFilmCritics": 0,
        "await": null
      },
      "votes": {
        "kp": 191476,
        "imdb": 3033,
        "filmCritics": 0,
        "russianFilmCritics": 0,
        "await": 0
      },
      "movieLength": 20,
      "id": 46223,
      "type": "cartoon",
      "name": "\u0411\u0440\u0435\u043c\u0435\u043d\u0441\u043a\u0438\u0435 \u043c\u0443\u0437\u044b\u043a\u0430\u043d\u0442\u044b",
      "description": "\u041c\u0443\u0437\u044b\u043a\u0430\u043b\u044c\u043d\u0430\u044f \u0444\u0430\u043d\u0442\u0430\u0437\u0438\u044f, \u043b\u044e\u0431\u0438\u043c\u0430\u044f \u043d\u0435 \u043e\u0434\u043d\u0438\u043c \u043f\u043e\u043a\u043e\u043b\u0435\u043d\u0438\u0435\u043c \u0437\u0440\u0438\u0442\u0435\u043b\u0435\u0439, \u043e \u043d\u0435\u043e\u0431\u044b\u043a\u043d\u043e\u0432\u0435\u043d\u043d\u044b\u0445, \u043e\u0447\u0435\u043d\u044c \u043e\u043f\u0430\u0441\u043d\u044b\u0445 \u0438 \u0432\u0435\u0441\u0435\u043b\u044b\u0445 \u043f\u0440\u0438\u043a\u043b\u044e\u0447\u0435\u043d\u0438\u044f\u0445 \u0431\u0440\u0435\u043c\u0435\u043d\u0441\u043a\u0438\u0445 \u043c\u0443\u0437\u044b\u043a\u0430\u043d\u0442\u043e\u0432: \u0422\u0440\u0443\u0431\u0430\u0434\u0443\u0440\u0430, \u043a\u043e\u0442\u0430, \u0441\u043e\u0431\u0430\u043a\u0438, \u043f\u0435\u0442\u0443\u0445\u0430 \u0438 \u043e\u0441\u043b\u0430. \u041c\u0443\u0437\u044b\u043a\u0430\u043d\u0442\u044b \u043f\u0443\u0442\u0435\u0448\u0435\u0441\u0442\u0432\u0443\u044e\u0442 \u043f\u043e \u0413\u0435\u0440\u043c\u0430\u043d\u0438\u0438 \u0432\u0440\u0435\u043c\u0435\u043d \u0431\u0440\u0430\u0442\u044c\u0435\u0432 \u0413\u0440\u0438\u043c\u043c \u0438 \u043f\u043e\u044e\u0442 \u0432\u043f\u043e\u043b\u043d\u0435 \u0441\u043e\u0432\u0440\u0435\u043c\u0435\u043d\u043d\u044b\u0435 \u043f\u0435\u0441\u043d\u0438. \u0412\u0440\u0435\u043c\u044f \u043e\u0442 \u0432\u0440\u0435\u043c\u0435\u043d\u0438 \u0441\u043e\u0432\u0435\u0440\u0448\u0430\u044e\u0442 \u043f\u043e\u0434\u0432\u0438\u0433\u0438. \u0412\u0441\u0435 \u0431\u044b\u043b\u043e \u0445\u043e\u0440\u043e\u0448\u043e, \u043d\u043e \u0432\u043e \u0432\u0440\u0435\u043c\u044f \u043e\u0434\u043d\u043e\u0433\u043e \u0446\u0438\u0440\u043a\u043e\u0432\u043e\u0433\u043e \u043f\u0440\u0435\u0434\u0441\u0442\u0430\u0432\u043b\u0435\u043d\u0438\u044f \u043f\u0440\u0438\u0433\u043b\u044f\u043d\u0443\u043b\u0430\u0441\u044c \u043d\u0430\u0448\u0435\u043c\u0443 \u0433\u0435\u0440\u043e\u044e \u043f\u0440\u0438\u043d\u0446\u0435\u0441\u0441\u0430...",
      "year": 1969,
      "poster": {
        "url": "https://st.kp.yandex.net/images/film_big/46223.jpg",
        "previewUrl": "https://st.kp.yandex.net/images/film_iphone/iphone360_46223.jpg"
      },
      "genres": [
        {
          "name": "\u043c\u0443\u043b\u044c\u0442\u0444\u0438\u043b\u044c\u043c"
        },
        {
          "name": "\u0434\u0435\u0442\u0441\u043a\u0438\u0439"
        },
        {
          "name": "\u043a\u043e\u0440\u043e\u0442\u043a\u043e\u043c\u0435\u0442\u0440\u0430\u0436\u043a\u0430"
        },
        {
          "name": "\u043c\u044e\u0437\u0438\u043a\u043b"
        },
        {
          "name": "\u0444\u044d\u043d\u0442\u0435\u0437\u0438"
        }
      ],
      "countries": [
        {
          "name": "\u0421\u0421\u0421\u0420"
        }
      ],
      "alternativeName": null,
      "enName": null,
      "names": [
        {
          "name": "\u0411\u0440\u0435\u043c\u0435\u043d\u0441\u043a\u0438\u0435 \u043c\u0443\u0437\u044b\u043a\u0430\u043d\u0442\u044b"
        }
      ],
      "shortDescription": "\u041f\u0440\u0438\u043d\u0446\u0435\u0441\u0441\u0430 \u0431\u0435\u0436\u0438\u0442 \u0438\u0437 \u0434\u0432\u043e\u0440\u0446\u0430 \u0441 \u0422\u0440\u0443\u0431\u0430\u0434\u0443\u0440\u043e\u043c \u0438 \u0435\u0433\u043e \u0440\u043e\u043a-\u0433\u0440\u0443\u043f\u043f\u043e\u0439. \u041d\u0435\u0441\u0442\u0430\u0440\u0435\u044e\u0449\u0430\u044f \u0441\u043a\u0430\u0437\u043a\u0430-\u043c\u044e\u0437\u0438\u043a\u043b, \u0433\u0434\u0435 \u043a\u0430\u0436\u0434\u0430\u044f \u043f\u0435\u0441\u043d\u044f \u2014 \u0445\u0438\u0442",
      "logo": {
        "url": "https://avatars.mds.yandex.net/get-ott/1652588/2a000001700f7264e2eb2908f41483c68dd0/orig"
      },
      "watchability": {
        "items": [
          {
            "name": "PREMIER",
            "logo": {
              "url": "https://avatars.mds.yandex.net/get-ott/239697/0f86e907-9531-47e9-87bd-5101a08d4e30/orig"
            },
            "url": "https://premier.one/show/11213?utm_source=yandex&utm_medium=yandex_feed_search&utm_campaign=yandex_feed"
          }
        ]
      }
    }
  ],
  "total": 14246,
  "limit": 10,
  "page": 2,
  "pages": 1425
}